CHANGES.rst
MANIFEST.in
README.rst
setup.py
./elevator/__init__.py
./elevator/api.py
./elevator/args.py
./elevator/config.py
./elevator/constants.py
./elevator/db.py
./elevator/frontend.py
./elevator/log.py
./elevator/message.py
./elevator/server.py
./elevator/backend/__init__.py
./elevator/backend/atm.py
./elevator/backend/protocol.py
./elevator/backend/supervisor.py
./elevator/backend/worker.py
./elevator/helpers/__init__.py
./elevator/helpers/internals.py
./elevator/utils/__init__.py
./elevator/utils/daemon.py
./elevator/utils/decorators.py
./elevator/utils/patterns.py
./elevator/utils/snippets.py
./elevator_cli/__init__.py
./elevator_cli/args.py
./elevator_cli/client.py
./elevator_cli/errors.py
./elevator_cli/helpers.py
./elevator_cli/io.py
./elevator_cli/main.py
./elevator_cli/message.py
Elevator.egg-info/PKG-INFO
Elevator.egg-info/SOURCES.txt
Elevator.egg-info/dependency_links.txt
Elevator.egg-info/entry_points.txt
Elevator.egg-info/requires.txt
Elevator.egg-info/top_level.txt
Elevator.egg-info/zip-safe
docs/Makefile