Metadata-Version: 1.1
Name: Elevator
Version: 0.5d
Summary: On disk key/value store based on levelDB backend
Home-page: http://github.com/oleiade/Elevator
Author: Oleiade
Author-email: tcrevon@gmail.com
License: MIT
Keywords: elevator leveldb database key-value
Platform: UNKNOWN
Classifier: Topic :: Database :: Database Engines/Servers
Classifier: Development Status :: 5 - Production/Stable
Classifier: Programming Language :: Python :: 2.7
Classifier: License :: OSI Approved :: MIT License
Classifier: Operating System :: Unix
